ipydatetime/__init__.py
ipydatetime/_frontend.py
ipydatetime/_version.py
ipydatetime/base_widget.py
ipydatetime/datetime_widget.py
ipydatetime/time_widget.py
ipydatetime/trait_types.py
ipydatetime/nbextension/__init__.py
ipydatetime/nbextension/static/extension.js
ipydatetime/nbextension/static/index.js
ipydatetime/nbextension/static/index.js.LICENSE.txt
ipydatetime/nbextension/static/index.js.map
ipydatetime/tests/__init__.py
ipydatetime/tests/conftest.py
ipydatetime/tests/test_datetime.py
ipydatetime/tests/test_naive.py
ipydatetime/tests/test_nbextension_path.py
ipydatetime/tests/test_serializers.py
ipydatetime/tests/test_time.py
ipydatetime-1.2.0.data/data/etc/jupyter/nbconfig/notebook.d/ipydatetime.json
ipydatetime-1.2.0.data/data/share/jupyter/lab/extensions/jupyter-widget-datetime-1.2.0.tgz
ipydatetime-1.2.0.data/data/share/jupyter/nbextensions/ipydatetime/extension.js
ipydatetime-1.2.0.data/data/share/jupyter/nbextensions/ipydatetime/index.js
ipydatetime-1.2.0.data/data/share/jupyter/nbextensions/ipydatetime/index.js.LICENSE.txt
ipydatetime-1.2.0.data/data/share/jupyter/nbextensions/ipydatetime/index.js.map
ipydatetime-1.2.0.dist-info/LICENSE.txt
ipydatetime-1.2.0.dist-info/METADATA
ipydatetime-1.2.0.dist-info/WHEEL
ipydatetime-1.2.0.dist-info/top_level.txt
ipydatetime-1.2.0.dist-info/RECORD
